{
    "name" : "RedSpacecraft",
    "fragmentShader" : "GenericFShader.glsl",
    "vertexShader" : "GenericVShader.glsl",
    "faces" : [
        {
            "vertexCoords" : [
                [  0.0,  -5.0,   1.0 ],
                [  0.0, -15.0,   1.0 ],
                [  1.0,  -5.0,   0.0 ],
                [  1.0, -15.0,   0.0 ],
                [  0.0,  -5.0,  -1.0 ],
                [  0.0, -15.0,  -1.0 ],
                [ -1.0,  -5.0,   0.0 ],
                [ -1.0, -15.0,   0.0 ],
                [  0.0,  -5.0,   1.0 ],
                [  0.0, -15.0,   1.0 ]
            ],
            "vertexColors" : [
                [  1.0, 0.3, 0.3 ],
                [  1.0, 0.3, 0.3 ],
                [  1.0, 0.3, 0.3 ],
                [  1.0, 0.3, 0.3 ],
                [  1.0, 0.3, 0.3 ],
                [  1.0, 0.3, 0.3 ],
                [  1.0, 0.3, 0.3 ],
                [  1.0, 0.3, 0.3 ],
                [  1.0, 0.3, 0.3 ],
                [  1.0, 0.3, 0.3 ]
            ]
        },
        {
            "vertexCoords" : [
                [  1.0, -15.0,   0.0 ],
                [  0.0, -15.0,   1.0 ],
                [  0.0, -15.0,  -1.0 ],
                [ -1.0, -15.0,   0.0 ]
            ],
            "vertexColors" : [
                [  0.0, 0.0, 0.0 ],
                [  0.0, 0.0, 0.0 ],
                [  0.0, 0.0, 0.0 ],
                [  0.0, 0.0, 0.0 ]
            ]
        },
        {
            "vertexCoords" : [
                [  0.0,  -5.0,   1.0 ],
                [  1.0,  -5.0,   0.0 ],
                [  0.0,   0.0,   0.0 ],
                [  0.0,  -5.0,  -1.0 ]
            ],
            "vertexColors" : [
                [  1.0, 0.3, 0.3 ],
                [  1.0, 0.3, 0.3 ],
                [  0.3, 0.3, 1.0 ],
                [  1.0, 0.3, 0.3 ]
            ]
        },
        {
            "vertexCoords" : [
                [  0.0,  -5.0,  -1.0 ],
                [ -1.0,  -5.0,   0.0 ],
                [  0.0,   0.0,   0.0 ],
                [  0.0,  -5.0,   1.0 ]
            ],
            "vertexColors" : [
                [  1.0, 0.3, 0.3 ],
                [  1.0, 0.3, 0.3 ],
                [  0.3, 0.3, 1.0 ],
                [  1.0, 0.3, 0.3 ]
            ]
        },
        {
            "vertexCoords" : [
                [ -4.0, -14.5,   1.0 ],
                [  0.0, -14.5,   0.2 ],
                [  0.0,  -9.0,   0.0 ],
                [  4.0, -14.5,   1.0 ]
            ],
            "vertexColors" : [
                [  0.3, 0.3, 1.0 ],
                [  1.0, 0.3, 0.3 ],
                [  1.0, 0.3, 0.3 ],
                [  0.3, 0.3, 1.0 ]
            ]
        },
        {
            "vertexCoords" : [
                [  4.0, -14.5,   1.0 ],
                [  0.0, -14.5,  -0.2 ],
                [  0.0,  -9.0,   0.0 ],
                [ -4.0, -14.5,   1.0 ]
            ],
            "vertexColors" : [
                [  0.3, 0.3, 1.0 ],
                [  1.0, 0.3, 0.3 ],
                [  1.0, 0.3, 0.3 ],
                [  0.3, 0.3, 1.0 ]
            ]
        },
        {
            "vertexCoords" : [
                [ -4.0, -14.5,   1.0   ],
                [  0.0, -14.5,  -0.2   ],
                [  0.0, -14.5,   0.2   ],
                [  4.0, -14.5,   1.0   ]
            ],
            "vertexColors" : [
                [  0.3, 0.3, 1.0 ],
                [  1.0, 0.3, 0.3 ],
                [  1.0, 0.3, 0.3 ],
                [  0.3, 0.3, 1.0 ]
            ]
        }
    ]
}
